README.txt
setup.cfg
setup.py
rfx/__init__.py
rfx/action.py
rfx/backend.py
rfx/client.py
rfx/config.py
rfx/control.py
rfx/crypto.py
rfx/deploy.py
rfx/launch.py
rfx/optarg.py
rfx/tabulate.py
rfx/test.py
rfx.egg-info/PKG-INFO
rfx.egg-info/SOURCES.txt
rfx.egg-info/dependency_links.txt
rfx.egg-info/requires.txt
rfx.egg-info/top_level.txt