Metadata-Version: 1.0
Name: rfx
Version: 1801.2
Summary: Reflex - Container Config and Secret Management - core lib
Home-page: https://reflex.cold.org/
Author: Brandon Gillespie
Author-email: bjg-pypi@cold.org
License: UNKNOWN
Keywords: docker,config,secrets
Platform: UNKNOWN
